<?xml version="1.0" encoding="utf-8" ?>
<dwsync>
<file name="wha_lo.gif" local="126948348000000000" remote="128067790800000000" testing="0" />
<file name="family.jpg" local="126984636000000000" remote="128067790800000000" testing="0" />
<file name="trail_britain.gif" local="127989823800000000" remote="128067790800000000" testing="0" />
<file name="trail_dragons.gif" local="127989823800000000" remote="128067790800000000" testing="0" />
<file name="trail_shiva.gif" local="127989823800000000" remote="128067790800000000" testing="0" />
<file name="trail_time.gif" local="127989823800000000" remote="128067790800000000" testing="0" />
<file name="trail_rainbow.gif" local="127989823800000000" remote="128067790800000000" testing="0" />
<file name="trail_nile.gif" local="127989823800000000" remote="128067790800000000" testing="0" />
<file name="africa_backpack.jpg" local="127989823800000000" remote="128067790800000000" testing="0" />
<file name="ancientegypt_backpack.jpg" local="127989823800000000" remote="128067790800000000" testing="0" />
<file name="back.gif" local="126948348000000000" remote="128067790800000000" testing="0" />
</dwsync>