<?xml version="1.0" encoding="utf-8" ?>
<dwsync>
<file name="friendstyle.css" local="128061731934836816" remote="128087727000000000" testing="0" />
<file name="bmfbanner.gif" local="127955524200000000" remote="128087727000000000" testing="0" />
<file name="spacer.gif" local="127955524200000000" remote="128087727000000000" testing="0" />
<file name="priceindiv_s.gif" local="127955524200000000" remote="128087727000000000" testing="0" />
<file name="pricedouble_s.gif" local="127955524200000000" remote="128087727000000000" testing="0" />
<file name="pricefam_s.gif" local="127955524200000000" remote="128087727000000000" testing="0" />
<file name="title1.gif" local="127955524200000000" remote="128087727000000000" testing="0" />
<file name="title2.gif" local="127955524200000000" remote="128087727000000000" testing="0" />
<file name="title3.gif" local="127955524200000000" remote="128087727000000000" testing="0" />
<file name="priceindiv.gif" local="127955524200000000" remote="128087727000000000" testing="0" />
<file name="title4.gif" local="127955524200000000" remote="128087727000000000" testing="0" />
<file name="pricedouble.gif" local="127955524200000000" remote="128087727000000000" testing="0" />
<file name="title5.gif" local="127955524200000000" remote="128087727000000000" testing="0" />
<file name="pricefam.gif" local="127955524200000000" remote="128087727000000000" testing="0" />
<file name="openevenings.jpg" local="127955524200000000" remote="128087727000000000" testing="0" />
<file name="howhelps.jpg" local="127955524200000000" remote="128087727000000000" testing="0" />
<file name="amerifriends.jpg" local="127955524200000000" remote="128087727000000000" testing="0" />
<file name="youngfriends.jpg" local="127955524200000000" remote="128087727000000000" testing="0" />
<file name="magazine.jpg" local="127955524200000000" remote="128087727000000000" testing="0" />
<file name="preview155x100.jpg" local="127955524200000000" remote="128087727000000000" testing="0" />
</dwsync>